contentzen/__init__.py
contentzen/client.py
contentzen/exceptions.py
contentzen-0.1.0.dist-info/METADATA
contentzen-0.1.0.dist-info/WHEEL
contentzen-0.1.0.dist-info/top_level.txt
contentzen-0.1.0.dist-info/RECORD
