Metadata-Version: 2.4
Name: contentzen
Version: 0.1.0
Summary: Official Python SDK for interacting with ContentZen headless CMS.
Home-page: https://contentzen.io
Author: ContentZen Team
Author-email: info@contentzen.io
License: MIT
Project-URL: Documentation, https://www.postman.com/winter-meteor-7066631/contentzen/collection/9m7enab/contentzen-api
Project-URL: Source, https://contentzen.io
Classifier: Programming Language :: Python :: 3
Classifier: License :: OSI Approved :: MIT License
Classifier: Operating System :: OS Independent
Requires-Python: >=3.7
Requires-Dist: requests
Provides-Extra: dev
Requires-Dist: pytest; extra == "dev"
